bin2/__init__.py
bin2-0.0.1.dist-info/LICENSE
bin2-0.0.1.dist-info/METADATA
bin2-0.0.1.dist-info/WHEEL
bin2-0.0.1.dist-info/top_level.txt
bin2-0.0.1.dist-info/RECORD
