Metadata-Version: 2.1
Name: bin2
Version: 0.0.1
Summary: Get 2' complemnt form of a integer
Home-page: https://github.com/codemee/bin2.git
Author: meebox
Author-email: meebox@gmail.com
License: UNKNOWN
Project-URL: Blog, https://dev.to/codemee/python-de-wei-yuan-yun-suan-5bgb
Platform: UNKNOWN
Classifier: Programming Language :: Python :: 3
Classifier: License :: OSI Approved :: MIT License
Classifier: Operating System :: OS Independent
Requires-Python: >=3.6
License-File: LICENSE
